run80by24/client/__init__.py
run80by24/client/__main__.py
run80by24/client/conf.py
run80by24/client/thread.py
run80by24_client-0.2.0.dist-info/DESCRIPTION.rst
run80by24_client-0.2.0.dist-info/METADATA
run80by24_client-0.2.0.dist-info/RECORD
run80by24_client-0.2.0.dist-info/WHEEL
run80by24_client-0.2.0.dist-info/entry_points.txt
run80by24_client-0.2.0.dist-info/metadata.json
run80by24_client-0.2.0.dist-info/top_level.txt
