Metadata-Version: 2.0
Name: run80by24-client
Version: 0.2.0
Summary: Client for publishing to text terminals over HTTP.
Home-page: https://80by24.net
Author: Sander Evers
Author-email: UNKNOWN
License: UNKNOWN
Keywords: terminal console
Platform: UNKNOWN
Classifier: Development Status :: 3 - Alpha
Classifier: Intended Audience :: Developers
Classifier: Topic :: Software Development :: Build Tools
Classifier: License :: OSI Approved :: GNU Affero General Public License v3 or later (AGPLv3+)
Classifier: Programming Language :: Python :: 3.4
Requires-Dist: pyyaml
Requires-Dist: websockets
Requires-Dist: run80by24-common
